periodic_table/__init__.py
periodic_table/main.py
periodic_table/table.py
periodic_table_dataclasses-1.0.dist-info/METADATA
periodic_table_dataclasses-1.0.dist-info/WHEEL
periodic_table_dataclasses-1.0.dist-info/entry_points.txt
periodic_table_dataclasses-1.0.dist-info/top_level.txt
periodic_table_dataclasses-1.0.dist-info/RECORD
