Metadata-Version: 2.1
Name: periodic-table-dataclasses
Version: 1.0
Summary: Python library of Periodic-Table-JSON
Home-page: https://github.com/NMRbox/Periodic-Table-JSON
Author: Gerard
Author-email: gweatherby@uchc.edu
License: CC BY-SA 3.0
Classifier: License :: Other/Proprietary License
Classifier: Programming Language :: Python :: 3.7
Classifier: Programming Language :: Python :: 3.8
Classifier: Programming Language :: Python :: 3.9
Classifier: Programming Language :: Python :: 3.10
Classifier: Programming Language :: Python :: 3.11
Classifier: Programming Language :: Python :: 3.12
Requires-Dist: dataclasses-json
